algorithms_sv/src/shiftadd_parallel/shiftadd_bp.sv
module shiftadd_parallel (
  input  logic [DATA_LENGTH-1:0]  x_i,       // Input
  input  logic [DATA_LENGTH-1:0]  m_i,       // Modulus
  input  logic [DATA_LENGTH-1:0]  m_bl_i,
  output logic [DATA_LENGTH-1:0]  result_o
);

localparam NUM_CHUNKS = 3;
localparam DATA_LENGTH = 64;

logic signed [DATA_LENGTH-1:0] chunk [NUM_CHUNKS-1:0];
logic fold_sign [NUM_CHUNKS-1:0];

logic [DATA_LENGTH-1:0] lo;
logic [DATA_LENGTH-1:0] mask;
logic [DATA_LENGTH-1:0] bitlength;

logic [DATA_LENGTH-1:0] msb_mask;    
logic [DATA_LENGTH-1:0] inner_mask;
logic [NUM_CHUNKS-1:0]  num_folds;

logic is_dilithium;
logic is_kyber;
logic is_fermat;   
logic is_mersenne; 

assign is_kyber     = (m_i == ((1 << 12) - (1 << 9) - (1 << 8) + 1));
assign is_dilithium = (m_i == ((1 << 23) - (1 << 13) + 1));

assign msb_mask     = 1 << (m_bl_i - 1);
assign inner_mask   = ((1 << (m_bl_i - 1)) - 1) & ~1;
assign is_fermat    = ((m_i & msb_mask) == msb_mask) && ((m_i & 1)==1) && ((m_i & inner_mask) == 0);
assign is_mersenne  = ((m_i ^ ((1 << m_bl_i) - 1)) == 0);
assign bitlength    = is_fermat ? (m_bl_i - 1) : m_bl_i;
assign mask         = is_mersenne ? m_i : ((1 << bitlength)-1);


generate
    for (genvar i = 0; i < NUM_CHUNKS; i++) begin
      if(i == 0) begin
        assign chunk[i] = (x_i & ((1 << bitlength) - 1));
      end else begin
        assign chunk[i] = ((x_i >> ((i) * bitlength)) & mask);
        // i is a genvar, which is just an integer during elaboration.
        // when we write i[0], we're accessing the LSB of i.
        assign fold_sign[i] = (i[0] == 1);
      end
    end
endgenerate

always_comb begin
  result_o = '0;
  for (int i = 0; i < NUM_CHUNKS + 1; i++) begin
    if (i == 0) begin
      result_o = chunk[i];
    end
    else if (i == NUM_CHUNKS) begin
      if (result_o >= m_i) begin
          result_o = result_o - m_i;
      end
      else if (is_fermat && $signed(result_o) < 0) begin
        result_o = result_o + $signed(m_i);
      end
      else begin
        result_o = result_o;
      end
    end
    else begin

      case(1'b1)
        is_mersenne: begin
          result_o += chunk[i];
        end
        is_fermat: begin
          if($signed(result_o) < 0) begin
            result_o = (result_o + $signed(m_i)) + (fold_sign[i] ? -chunk[i] : chunk[i]);
          end
          else begin
            result_o = result_o + (fold_sign[i] ? -chunk[i] : chunk[i]);
          end
        end
        is_dilithium: begin
          result_o = result_o + scale_chunk_dilithium(chunk[i], i);
        end
        is_kyber: begin
          result_o = result_o + scale_chunk_kyber(chunk[i], i);
        end
      endcase
    end
  end
end

// Computes scaled value of `chunk` by (2^13 - 1)^i
function automatic logic [23*2-1:0] scale_chunk_dilithium (
    input logic [31:0] chunk,
    input int unsigned i
);
    logic [63:0] tmp;
    tmp = chunk;
    for (int j = 0; j < i; j++) begin
        tmp = (tmp << 13) - tmp;
    end
    return tmp;
endfunction

// Computes scaled value of `chunk` by (2^9 + 2^8 - 1)^i
function automatic logic [63:0] scale_chunk_kyber (
    input logic [31:0] chunk,
    input int unsigned i
);
    logic [127:0] tmp;
    tmp = chunk;
    for (int j = 0; j < i; j++) begin
        tmp = (tmp << 9) + (tmp << 8) - tmp;
    end
    return tmp;
endfunction

endmodule : shiftadd_parallel

algorithms_sv/src/shiftadd_parallel/tb.sv

// import multiplier_pkg::*;

module shiftadd_bp_tb;
    logic                       clk_i;           // Rising edge active clk.
    logic                       rst_ni;          // Active low reset.
    logic                       start_i;         // Start signal.
    logic                       busy_o;          // Module busy. 
    logic                       finish_o;        // Module finish.
    logic [64-1:0]              indata_x_i;      // Input data -> operand a.
    logic [64-1:0]              indata_m_i;      // Input data -> operand b.
    logic [64-1:0]              indata_mu_i;     // Input data -> operand b.
    logic [64-1:0]              indata_m_bl_i;   // Input data -> operand b.
    logic [64-1:0]              outdata_r_o;     // Output data -> result a*b.

    logic [64-1:0]              reference_o;

    shiftadd_parallel uut (
      .x_i                    (indata_x_i),
      .m_i                    (indata_m_i),
      .m_bl_i                 (indata_m_bl_i),
      .result_o               (outdata_r_o)
    );

    initial forever #5 clk_i = ~clk_i;

    initial begin
        $dumpfile("shiftadd_bp_tb.vcd");
        $dumpvars(0, shiftadd_bp_tb);
    end

    integer inp_file;

    assign indata_m_bl_i = $clog2(indata_m_i);

    initial begin
    $display("\n=======================================");
    $display("[%04t] > Start shiftadd_bp_tb test", $time);
    $display("=======================================\n");

    clk_i     = 0;
    rst_ni    = 0;
    start_i   = 0;

    // indata_m_i = 64'h7FFFFFFF; // Mersenne
    indata_m_i = 32'h80000001; // Fermat

    inp_file = $fopen("input.txt", "r");
    if (inp_file == 0) begin
        $display("ERROR: Failed to open file.");
        $finish;
    end else begin
        $display("File opened.");
    end

    while (!$feof(inp_file)) begin
       $fscanf(inp_file, "%h", indata_x_i);
        #5
        if (indata_x_i != 0) begin
          $display("[%04t] > Input data    : %h", $time, indata_x_i);
          reference_o = indata_x_i % indata_m_i;

          $display("[%04t] > Received data : %h", $time, outdata_r_o);
          $display("[%04t] > Reference data: %h", $time, reference_o);
          if (outdata_r_o == reference_o)
              $display("[%04t] > Data is VALID", $time);
          else
              $display("[%04t] > Data is INVALID", $time);
          $display("");
        end
    end

    $display("\n=======================================");
    $display("[%04t] > Finish shiftadd_bp_tb test", $time);
    $display("=======================================\n");

    #100;
    $finish;
end

endmodule : shiftadd_bp_tb

algorithms_sv/src/shiftadd_parallel/shiftadd_bp_tb.vcd
$date
	Sun Jun 22 14:17:43 2025
$end
$version
	Icarus Verilog
$end
$timescale
	1s
$end
$scope module shiftadd_bp_tb $end
$var wire 64 ! outdata_r_o [63:0] $end
$var wire 64 " indata_m_bl_i [63:0] $end
$var reg 1 # clk_i $end
$var reg 64 $ indata_m_i [63:0] $end
$var reg 64 % indata_x_i [63:0] $end
$var reg 64 & reference_o [63:0] $end
$var reg 1 ' rst_ni $end
$var reg 1 ( start_i $end
$var integer 32 ) inp_file [31:0] $end
$scope module uut $end
$var wire 64 * inner_mask [63:0] $end
$var wire 1 + is_fermat $end
$var wire 64 , m_bl_i [63:0] $end
$var wire 64 - m_i [63:0] $end
$var wire 64 . x_i [63:0] $end
$var wire 64 / msb_mask [63:0] $end
$var wire 64 0 mask [63:0] $end
$var wire 1 1 is_mersenne $end
$var wire 1 2 is_kyber $end
$var wire 1 3 is_dilithium $end
$var wire 64 4 bitlength [63:0] $end
$var parameter 32 5 DATA_LENGTH $end
$var parameter 32 6 NUM_CHUNKS $end
$var reg 64 7 result_o [63:0] $end
$scope function scale_chunk_dilithium $end
$scope begin $ivl_for_loop1 $end
$upscope $end
$upscope $end
$scope function scale_chunk_kyber $end
$scope begin $ivl_for_loop2 $end
$upscope $end
$upscope $end
$scope begin genblk1[0] $end
$var parameter 2 8 i $end
$scope begin genblk1 $end
$upscope $end
$upscope $end
$scope begin genblk1[1] $end
$var parameter 2 9 i $end
$scope begin genblk1 $end
$upscope $end
$upscope $end
$scope begin genblk1[2] $end
$var parameter 3 : i $end
$scope begin genblk1 $end
$upscope $end
$upscope $end
$scope begin $ivl_for_loop0 $end
$var integer 32 ; i [31:0] $end
$upscope $end
$upscope $end
$upscope $end
$enddefinitions $end
$comment Show the parameter values. $end
$dumpall
b10 :
b1 9
b0 8
b11 6
b1000000 5
$end
#0
$dumpvars
b100 ;
b1001011010011001111110110111010 7
b11111 4
03
02
01
b1111111111111111111111111111111 0
b10000000000000000000000000000000 /
b1111101000000010111110110101000110111111010100101111010001011001 .
b10000000000000000000000000000001 -
b100000 ,
1+
b1111111111111111111111111111110 *
b10000000000000000000000000000011 )
0(
0'
bx &
b1111101000000010111110110101000110111111010100101111010001011001 %
b10000000000000000000000000000001 $
0#
b100000 "
b1001011010011001111110110111010 !
$end
#5
b100 ;
b1101110000100110110101001101 !
b1101110000100110110101001101 7
b111100011010000011001110000111001111111011000110011101101101000 %
b111100011010000011001110000111001111111011000110011101101101000 .
b1001011010011001111110110111010 &
1#
#10
b100 ;
b1000110101101101110011100101101 !
b1000110101101101110011100101101 7
b111101001111110001010101010001110111011101100110011110001110010 %
b111101001111110001010101010001110111011101100110011110001110010 .
b1101110000100110110101001101 &
0#
#15
b100 ;
b1111110111111111010101110010010 !
b1111110111111111010101110010010 7
b100111111110101101100101001110010010111111010001100000111000 %
b100111111110101101100101001110010010111111010001100000111000 .
b1000110101101101110011100101101 &
1#
#20
b100 ;
b10000100110110000001010001 !
b10000100110110000001010001 7
b1110011101111111111011011001110111011111100110101101110111000 %
b1110011101111111111011011001110111011111100110101101110111000 .
b1111110111111111010101110010010 &
0#
#25
b100 ;
b1010101010010101000011001000101 !
b1010101010010101000011001000101 7
b11011001011010010100100100011001000001111111110010101011010000 %
b11011001011010010100100100011001000001111111110010101011010000 .
b10000100110110000001010001 &
1#
#30
b100 ;
b10010111010000111101001110010 !
b10010111010000111101001110010 7
b100111101100011110101000100110110110001101100000010001100001100 %
b100111101100011110101000100110110110001101100000010001100001100 .
b1010101010010101000011001000101 &
0#
#35
b100 ;
b101111100000010110100001100001 !
b101111100000010110100001100001 7
b111100101011000110100101110110010100010001100110000111000111000 %
b111100101011000110100101110110010100010001100110000111000111000 .
b10010111010000111101001110010 &
1#
#40
b100 ;
b110011010100111110100000100110 !
b110011010100111110100000100110 7
b1000100101100101010111001000011111000110000111101010000100110011 %
b1000100101100101010111001000011111000110000111101010000100110011 .
b101111100000010110100001100001 &
0#
#45
b100 ;
b1011011110011111100100001011110 !
b1011011110011111100100001011110 7
b1100010101100000000001110110000011100110100011111101011100011100 %
b1100010101100000000001110110000011100110100011111101011100011100 .
b110011010100111110100000100110 &
1#
#50
b100 ;
b111111001110001011110101010010 !
b111111001110001011110101010010 7
b100110011011101010101011011101010010011100000001001011000000 %
b100110011011101010101011011101010010011100000001001011000000 .
b1011011110011111100100001011110 &
0#
#55
b100 ;
b1000101001110101110110011010011 !
b1000101001110101110110011010011 7
b10100001110001100101111101110000010110000111100001110010001010 %
b10100001110001100101111101110000010110000111100001110010001010 .
b111111001110001011110101010010 &
1#
#60
b100 ;
b1010111000011111111101011001 !
b1010111000011111111101011001 7
b1000100110100101010001001000011000011110001011001000100001100011 %
b1000100110100101010001001000011000011110001011001000100001100011 .
b1000101001110101110110011010011 &
0#
#65
b100 ;
b101001011000011101000101010010 !
b101001011000011101000101010010 7
b100000110111001110101011010100110101100110101010111110010100100 %
b100000110111001110101011010100110101100110101010111110010100100 .
b1010111000011111111101011001 &
1#
#70
b100 ;
b1110100011010011000111011100010 !
b1110100011010011000111011100010 7
b1010000011111100100101100100110000110110011000101011101101110111 %
b1010000011111100100101100100110000110110011000101011101101110111 .
b101001011000011101000101010010 &
0#
#75
b100 ;
b100110000010000110110010100100 !
b100110000010000110110010100100 7
b1010111000101011011110010101111110000010010111110101111101100000 %
b1010111000101011011110010101111110000010010111110101111101100000 .
b1110100011010011000111011100010 &
1#
#80
b100 ;
b1100101111010010101011101101 !
b1100101111010010101011101101 7
b1101111010010111111011011100001000100011000110010011001011101 %
b1101111010010111111011011100001000100011000110010011001011101 .
b100110000010000110110010100100 &
0#
#85
b100 ;
b1111101000101011010110011 !
b1111101000101011010110011 7
b101101100101110010111111000000011000101111111110111010010011 %
b101101100101110010111111000000011000101111111110111010010011 .
b1100101111010010101011101101 &
1#
#90
b100 ;
b1011111110000110110011100010101 !
b1011111110000110110011100010101 7
b11011010010100110111011011011001001100111011010010001010000000 %
b11011010010100110111011011011001001100111011010010001010000000 .
b1111101000101011010110011 &
0#
#95
b100 ;
b1010010111000011011101111000101 !
b1010010111000011011101111000101 7
b1100111000100011001010111101101101101111001010000001001101111000 %
b1100111000100011001010111101101101101111001010000001001101111000 .
b1011111110000110110011100010101 &
1#
#100
b100 ;
b1100100111001100001100000110011 !
b1100100111001100001100000110011 7
b10100000110101011100101111111000110101010100001111111000101110 %
b10100000110101011100101111111000110101010100001111111000101110 .
b1010010111000011011101111000101 &
0#
#105
b100 ;
b1101110101011011011111010011101 !
b1101110101011011011111010011101 7
b1101111010101110101000001000000100110010110010110011010111100 %
b1101111010101110101000001000000100110010110010110011010111100 .
b1100100111001100001100000110011 &
1#
#110
b100 ;
b1001100101011001100011001000001 !
b1001100101011001100011001000001 7
b1010011011011100010010000100110000011010011001010101011011010110 %
b1010011011011100010010000100110000011010011001010101011011010110 .
b1101110101011011011111010011101 &
0#
#115
b100 ;
b1101111111011111101000100110011 !
b1101111111011111101000100110011 7
b1110100100100010111000101001001111000010001101011001011001010110 %
b1110100100100010111000101001001111000010001101011001011001010110 .
b1001100101011001100011001000001 &
1#
#120
b100 ;
b101100010000101101110110100110 !
b101100010000101101110110100110 7
b1010100101001100101110111100011001111110110111000101010100110000 %
b1010100101001100101110111100011001111110110111000101010100110000 .
b1101111111011111101000100110011 &
0#
#125
b100 ;
b1101100001111000001110101011100 !
b1101100001111000001110101011100 7
b1000100000010001111110101010101101111100011000000001001010110000 %
b1000100000010001111110101010101101111100011000000001001010110000 .
b101100010000101101110110100110 &
1#
#130
b100 ;
b1111101001101011000001001111100 !
b1111101001101011000001001111100 7
b101011011011001000001001100001100101010111001111000110000000000 %
b101011011011001000001001100001100101010111001111000110000000000 .
b1101100001111000001110101011100 &
0#
#135
b100 ;
b11000010010000001010100011011 !
b11000010010000001010100011011 7
b111001001010111110110000001101001111100111101111100010101001110 %
b111001001010111110110000001101001111100111101111100010101001110 .
b1111101001101011000001001111100 &
1#
#140
b100 ;
b1011000010110011110101001110111 !
b1011000010110011110101001110111 7
b1100110111111101110011100011100001011110110010101111000000100 %
b1100110111111101110011100011100001011110110010101111000000100 .
b11000010010000001010100011011 &
0#
#145
b100 ;
b1011101010101011000100101100101 !
b1011101010101011000100101100101 7
b101101000001110000011110111010010010001011100011010100001001100 %
b101101000001110000011110111010010010001011100011010100001001100 .
b1011000010110011110101001110111 &
1#
#150
b100 ;
b1110100101001110000000011111100 !
b1110100101001110000000011111100 7
b1111101000011101111010110000111001101000111000101101011100010100 %
b1111101000011101111010110000111001101000111000101101011100010100 .
b1011101010101011000100101100101 &
0#
#155
b100 ;
b11001111001101101011101110110 !
b11001111001101101011101110110 7
b111111101001101001000110010011110011000100000010001110111000011 %
b111111101001101001000110010011110011000100000010001110111000011 .
b1110100101001110000000011111100 &
1#
#160
b100 ;
b1010110111000011001101011011 !
b1010110111000011001101011011 7
b110101110111100111101001110011011100010010101100001110100100111 %
b110101110111100111101001110011011100010010101100001110100100111 .
b11001111001101101011101110110 &
0#
#165
b100 ;
b111110101111100111110011010011 !
b111110101111100111110011010011 7
b1001110110000110110111101100101111111001110011000011101001101000 %
b1001110110000110110111101100101111111001110011000011101001101000 .
b1010110111000011001101011011 &
1#
#170
b100 ;
b1100010100101101000011100110001 !
b1100010100101101000011100110001 7
b10001111101100011000001111010100101010011011110100100100011010 %
b10001111101100011000001111010100101010011011110100100100011010 .
b111110101111100111110011010011 &
0#
#175
b100 ;
b111000101100110100000100011101 !
b111000101100110100000100011101 7
b1110000000000010101010100001101101111000101110001001010101010000 %
b1110000000000010101010100001101101111000101110001001010101010000 .
b1100010100101101000011100110001 &
1#
#180
b100 ;
b110000110010111101000111010001 !
b110000110010111101000111010001 7
b101111101110000010101111110100001101111101011001000000110100000 %
b101111101110000010101111110100001101111101011001000000110100000 .
b111000101100110100000100011101 &
0#
#185
b100 ;
b110011001010000010111010110010 !
b110011001010000010111010110010 7
b111000011101000010011011011010010010100111110001100101000011001 %
b111000011101000010011011011010010010100111110001100101000011001 .
b110000110010111101000111010001 &
1#
#190
b100 ;
b110001010011100111111111010110 !
b110001010011100111111111010110 7
b111110000001010011001110010010100101001011000110100111000011110 %
b111110000001010011001110010010100101001011000110100111000011110 .
b110011001010000010111010110010 &
0#
#195
b100 ;
b100000010110110111011010000010 !
b100000010110110111011010000010 7
b10001010010111101100011110101001100101100010101101101001010110 %
b10001010010111101100011110101001100101100010101101101001010110 .
b110001010011100111111111010110 &
1#
#200
b100 ;
b1110001010011001100011101100001 !
b1110001010011001100011101100001 7
b1000000000000000100111111111010011110001010011100000011101001000 %
b1000000000000000100111111111010011110001010011100000011101001000 .
b100000010110110111011010000010 &
0#
#205
b100 ;
b101000100000100101110101111101 !
b101000100000100101110101111101 7
b1101001010110001111000110100001101001101111001100010010000000000 %
b1101001010110001111000110100001101001101111001100010010000000000 .
b1110001010011001100011101100001 &
1#
#210
b100 ;
b1100000110101110101001110100010 !
b1100000110101110101001110100010 7
b1111000000111010000011101110010101000001010010110111000101101000 %
b1111000000111010000011101110010101000001010010110111000101101000 .
b101000100000100101110101111101 &
0#
#215
b100 ;
b1000011011110100100001100111110 !
b1000011011110100100001100111110 7
b1001010000001111010111010111001011101011100110001111111000100001 %
b1001010000001111010111010111001011101011100110001111111000100001 .
b1100000110101110101001110100010 &
1#
#220
b100 ;
b1010010110101110000001001100000 !
b1010010110101110000001001100000 7
b1011101000101000010110101111101011000111001001111011100001010010 %
b1011101000101000010110101111101011000111001001111011100001010010 .
b1000011011110100100001100111110 &
0#
#225
b100 ;
b11100010110001011011110101010 !
b11100010110001011011110101010 7
b101001110111101010100101111101011000011110100110101110110011110 %
b101001110111101010100101111101011000011110100110101110110011110 .
b1010010110101110000001001100000 &
1#
#230
b100 ;
b1111101011101110101001101001100 !
b1111101011101110101001101001100 7
b101000011000110010011000100010100011111000000111110101111010100 %
b101000011000110010011000100010100011111000000111110101111010100 .
b11100010110001011011110101010 &
0#
#235
b100 ;
b100001111111010111000010101110 !
b100001111111010111000010101110 7
b1100011100111001100011000010101000001101110011110100001111 %
b1100011100111001100011000010101000001101110011110100001111 .
b1111101011101110101001101001100 &
1#
#240
b100 ;
b0 !
b0 7
b0 %
b0 .
b100001111111010111000010101110 &
0#
